{"country":"Other","followers":0,"friends":0,"hashtags":[],"lang":"en","likes":0,"location":"Other","name":"VoteTrump","retweets":0,"source":"<a href=\"http://twitter.com/download/iphone\" rel=\"nofollow\">Twitter for iPhone</a>","text":"@realDonaldTrump please be aware you are being followed by some jihadi nutcase. https://t.co/n8sm4Efrrf","time_zone":"Other","words":["@realdonaldtrump","please","be","aware","you","are","being","followed","by","some","jihadi","nutcase.","https://t.co/n8sm4efrrf"],"filtered_words":["@realdonaldtrump","please","aware","followed","jihadi","nutcase.","https://t.co/n8sm4efrrf"],"features":{"type":1,"values":[-0.009751552449805396,-0.01859688226665769,-0.03699229870523725,0.011059214494058063,1.1887028813362122E-4]},"prediction":9}
{"country":"Other","followers":0,"friends":0,"hashtags":[],"lang":"es","likes":0,"location":"Other","name":"camila pacheco","retweets":0,"source":"<a href=\"http://www.tweetcaster.com\" rel=\"nofollow\">TweetCaster for Android</a>","text":"No tiene sentido aguantar una mala situación cuando no hay nada que hacer para mejorarlo. Donald Trump","time_zone":"Other","words":["no","tiene","sentido","aguantar","una","mala","situación","cuando","no","hay","nada","que","hacer","para","mejorarlo.","donald","trump"],"filtered_words":["tiene","sentido","aguantar","una","mala","situación","cuando","hay","nada","que","hacer","para","mejorarlo.","donald","trump"],"features":{"type":1,"values":[0.015870415046811102,0.039681583642959595,0.016606284026056527,-0.0201363910920918,-0.024072101650138695]},"prediction":16}
{"country":"Other","followers":0,"friends":0,"hashtags":[],"lang":"fr","likes":0,"location":"Other","name":"sidener loe","retweets":0,"source":"<a href=\"http://twitter.com/download/android\" rel=\"nofollow\">Twitter for Android</a>","text":"RT @DokPhone: En stock iPhone 5 Patron magnétique d'aide au montage pas à pas : https://t.co/3Gqf5emxwy","time_zone":"Other","words":["rt","@dokphone:","en","stock","iphone","5","patron","magnétique","d'aide","au","montage","pas","à","pas",":","https://t.co/3gqf5emxwy"],"filtered_words":["rt","@dokphone:","en","stock","iphone","5","patron","magnétique","d'aide","au","montage","pas","à","pas",":","https://t.co/3gqf5emxwy"],"features":{"type":1,"values":[0.016614671156276017,0.06760576838860288,0.09678939764853567,0.007617622155521531,-0.072438869276084]},"prediction":2}
{"country":"Other","followers":0,"friends":3,"hashtags":["android","androidgames","gameinsight"],"lang":"de","likes":0,"location":"Other","name":"sim one","retweets":0,"source":"","text":"Ich habe 15,905 Goldmünzen gesammelt!  https://t.co/qd7f4seRlE #android, #androidgames, #gameinsight","time_zone":"Other","words":["ich","habe","15,905","goldmünzen","gesammelt!","","https://t.co/qd7f4serle","#android,","#androidgames,","#gameinsight"],"filtered_words":["ich","habe","15,905","goldmünzen","gesammelt!","","https://t.co/qd7f4serle","#android,","#androidgames,","#gameinsight"],"features":{"type":1,"values":[-0.0417262377217412,-0.10656842812895775,-0.03913401961326599,0.057395173050463204,0.10936679439619185]},"prediction":12}
{"country":"Other","followers":1,"friends":9,"hashtags":["android","androidgames","gameinsight"],"lang":"en","likes":0,"location":"Other","name":"JoJo-K","retweets":0,"source":"","text":"I've collected 75,438 gold coins!  https://t.co/mklNuUYi8g #android, #androidgames, #gameinsight","time_zone":"Other","words":["i've","collected","75,438","gold","coins!","","https://t.co/mklnuuyi8g","#android,","#androidgames,","#gameinsight"],"filtered_words":["collected","75,438","gold","coins!","","https://t.co/mklnuuyi8g","#android,","#androidgames,","#gameinsight"],"features":{"type":1,"values":[-0.07107610545224613,-0.07746593736939959,-0.05807092428828279,0.018664026839865577,0.12757363584306505]},"prediction":17}
{"country":"Other","followers":1,"friends":20,"hashtags":["android","androidgames","gameinsight"],"lang":"ru","likes":0,"location":"Other","name":"mihail buzinov","retweets":0,"source":"","text":"Урожай собран - 1 420 еды! Ты тоже проверь свои грядки!  https://t.co/OCOhmcEsxQ #android, #androidgames, #gameinsight","time_zone":"Other","words":["урожай","собран","-","1","420","еды!","ты","тоже","проверь","свои","грядки!","","https://t.co/ocohmcesxq","#android,","#androidgames,","#gameinsight"],"filtered_words":["урожай","собран","-","1","420","еды!","ты","тоже","проверь","свои","грядки!","","https://t.co/ocohmcesxq","#android,","#androidgames,","#gameinsight"],"features":{"type":1,"values":[-0.07221110194223002,-0.05301709228660911,-0.02845028610317968,0.047280107901315205,0.08484312414657325]},"prediction":17}
{"country":"Other","followers":3,"friends":4,"hashtags":["Android","androidgames","gameinsight"],"lang":"en","likes":0,"location":"Other","name":"Valsan Elena","retweets":0,"source":"","text":"I have completed the quest 'Rescuing the nei...' in the #Android game The Tribez.  https://t.co/KApMlVpFx5 #androidgames, #gameinsight","time_zone":"Other","words":["i","have","completed","the","quest","'rescuing","the","nei...'","in","the","#android","game","the","tribez.","","https://t.co/kapmlvpfx5","#androidgames,","#gameinsight"],"filtered_words":["completed","quest","'rescuing","nei...'","#android","game","tribez.","","https://t.co/kapmlvpfx5","#androidgames,","#gameinsight"],"features":{"type":1,"values":[-0.02119617909193039,-0.02311745472252369,0.006872248158536174,-0.004185265268791805,0.04154096238992431]},"prediction":6}
{"country":"Other","followers":4,"friends":13,"hashtags":[],"lang":"fr","likes":0,"location":"Brasilieber!!!","name":"SKOTNICKI SELIN","retweets":0,"source":"<a href=\"http://twitter.com/download/android\" rel=\"nofollow\">Twitter for Android</a>","text":"RT @DokPhone: En stock iPhone 5 Patron magnétique d'aide au montage pas à pas : https://t.co/3Gqf5emxwy","time_zone":"Other","words":["rt","@dokphone:","en","stock","iphone","5","patron","magnétique","d'aide","au","montage","pas","à","pas",":","https://t.co/3gqf5emxwy"],"filtered_words":["rt","@dokphone:","en","stock","iphone","5","patron","magnétique","d'aide","au","montage","pas","à","pas",":","https://t.co/3gqf5emxwy"],"features":{"type":1,"values":[0.016614671156276017,0.06760576838860288,0.09678939764853567,0.007617622155521531,-0.072438869276084]},"prediction":2}
{"country":"Other","followers":6,"friends":67,"hashtags":[],"lang":"in","likes":0,"location":"Other","name":"makgad","retweets":0,"source":"<a href=\"http://blackberry.com/twitter\" rel=\"nofollow\">Twitter for BlackBerry®</a>","text":"RT @aisyahbusyaa: @SyafiqahNidzam kat mana tu? Eh okay apa hahah btw akak penjual iphone and casing hahah kalau nak beli pm lah ye hahah","time_zone":"Other","words":["rt","@aisyahbusyaa:","@syafiqahnidzam","kat","mana","tu?","eh","okay","apa","hahah","btw","akak","penjual","iphone","and","casing","hahah","kalau","nak","beli","pm","lah","ye","hahah"],"filtered_words":["rt","@aisyahbusyaa:","@syafiqahnidzam","kat","mana","tu?","eh","okay","apa","hahah","btw","akak","penjual","iphone","casing","hahah","kalau","nak","beli","pm","lah","ye","hahah"],"features":{"type":1,"values":[0.00959786009448378,0.04459330415272194,0.06415097646253265,0.02315258003933274,-0.06900393258294334]},"prediction":2}
{"country":"Other","followers":7,"friends":18,"hashtags":[],"lang":"en","likes":0,"location":"Brooklyn, NY","name":"Galewyn Massey","retweets":0,"source":"<a href=\"http://twitter.com\" rel=\"nofollow\">Twitter Web Client</a>","text":"@RealGM4Hillary Another, Barbara Burke foray on her impersonator site, trolling an unsuspecting Republican like Bob Capano -- be afraid Bob!","time_zone":"Pacific Time (US & Canada)","words":["@realgm4hillary","another,","barbara","burke","foray","on","her","impersonator","site,","trolling","an","unsuspecting","republican","like","bob","capano","--","be","afraid","bob!"],"filtered_words":["@realgm4hillary","another,","barbara","burke","foray","impersonator","site,","trolling","unsuspecting","republican","like","bob","capano","--","afraid","bob!"],"features":{"type":1,"values":[0.011420855720643885,0.015283911809092388,0.007981870061485097,-0.019531168130924925,-0.020201694482238963]},"prediction":5}
{"country":"Other","followers":12,"friends":26,"hashtags":[],"lang":"en","likes":0,"location":"Other","name":"J&J Farm","retweets":0,"source":"<a href=\"http://twitter.com/download/android\" rel=\"nofollow\">Twitter for Android</a>","text":"No more passport page inserts for frequent travelers https://t.co/jNwKlb7aNf via the @FoxNews Android app","time_zone":"Other","words":["no","more","passport","page","inserts","for","frequent","travelers","https://t.co/jnwklb7anf","via","the","@foxnews","android","app"],"filtered_words":["passport","page","inserts","frequent","travelers","https://t.co/jnwklb7anf","via","@foxnews","android","app"],"features":{"type":1,"values":[0.009666834864765406,0.015522730071097612,0.01912542674690485,-0.0220146207138896,0.002493021916598082]},"prediction":5}
{"country":"Other","followers":13,"friends":231,"hashtags":[],"lang":"en","likes":0,"location":"Other","name":"Kerri Pinegar","retweets":0,"source":"<a href=\"http://twitter.com\" rel=\"nofollow\">Twitter Web Client</a>","text":"RT @gamingacademy11: Lead your clan to glory and victory with Vikings War of Clans Hack for Android and iOS\nhttp://t.co/BnDLw9i6fa","time_zone":"Other","words":["rt","@gamingacademy11:","lead","your","clan","to","glory","and","victory","with","vikings","war","of","clans","hack","for","android","and","ios","http://t.co/bndlw9i6fa"],"filtered_words":["rt","@gamingacademy11:","lead","clan","glory","victory","vikings","war","clans","hack","android","ios","http://t.co/bndlw9i6fa"],"features":{"type":1,"values":[0.007257629221735093,0.017822399019048765,0.027290053988018863,-0.03251964921275011,-0.029812567974798955]},"prediction":16}
{"country":"Other","followers":14,"friends":78,"hashtags":[],"lang":"ja","likes":0,"location":"JK①","name":"MICO","retweets":0,"source":"<a href=\"http://twitter.com/download/iphone\" rel=\"nofollow\">Twitter for iPhone</a>","text":"RT @luzabs: カラオケwith奏音69 モイ！iPhoneからキャス配信中 - https://t.co/ZymdAEAU1F","time_zone":"Other","words":["rt","@luzabs:","カラオケwith奏音69","モイ！iphoneからキャス配信中","-","https://t.co/zymdaeau1f"],"filtered_words":["rt","@luzabs:","カラオケwith奏音69","モイ！iphoneからキャス配信中","-","https://t.co/zymdaeau1f"],"features":{"type":1,"values":[0.05901318478087584,0.07404319786777099,0.04026535603528221,-0.02045910805463791,-0.032029511251797274]},"prediction":10}
{"country":"Other","followers":20,"friends":1264,"hashtags":[],"lang":"ru","likes":0,"location":"Иркутск, Иркутская область","name":"Алина Романова","retweets":0,"source":"<a href=\"https://mobile.twitter.com\" rel=\"nofollow\">Mobile Web (M2)</a>","text":"RT @games4mob: Скачать экономическую стратегию Мегаполис на Android https://t.co/zr88ql105F","time_zone":"Other","words":["rt","@games4mob:","скачать","экономическую","стратегию","мегаполис","на","android","https://t.co/zr88ql105f"],"filtered_words":["rt","@games4mob:","скачать","экономическую","стратегию","мегаполис","на","android","https://t.co/zr88ql105f"],"features":{"type":1,"values":[0.03955241696288188,0.010974206444289949,-0.013751731461120976,-0.00601522314051787,-0.031755036247583725]},"prediction":3}
{"country":"Other","followers":36,"friends":330,"hashtags":[],"lang":"es","likes":0,"location":"Other","name":"Mauricio Carmona","retweets":0,"source":"<a href=\"http://www.tweetcaster.com\" rel=\"nofollow\">TweetCaster for Android</a>","text":"Un pequeño esfuerzo es el mejor sustituto de las excusas. Donald Trump","time_zone":"Other","words":["un","pequeño","esfuerzo","es","el","mejor","sustituto","de","las","excusas.","donald","trump"],"filtered_words":["un","pequeño","esfuerzo","es","el","mejor","sustituto","de","las","excusas.","donald","trump"],"features":{"type":1,"values":[0.0322049300884828,0.019425038597546518,0.021708993551631767,-0.021010525020149846,-0.009461547092845041]},"prediction":16}
{"country":"Other","followers":41,"friends":20,"hashtags":[],"lang":"tr","likes":0,"location":"late 90's","name":"weaboo trash (ipek)","retweets":0,"source":"<a href=\"http://twitter.com\" rel=\"nofollow\">Twitter Web Client</a>","text":"bilemiyorum trump hariç snl bu sene çok iyi gidiyor https://t.co/fhf22IGw4G","time_zone":"Istanbul","words":["bilemiyorum","trump","hariç","snl","bu","sene","çok","iyi","gidiyor","https://t.co/fhf22igw4g"],"filtered_words":["bilemiyorum","trump","hariç","snl","bu","sene","çok","iyi","gidiyor","https://t.co/fhf22igw4g"],"features":{"type":1,"values":[0.02071435544639826,-0.02646482260897756,-0.01199727263301611,-0.006223626807332039,-0.007338790502399207]},"prediction":9}
{"country":"Other","followers":70,"friends":90,"hashtags":[],"lang":"en","likes":0,"location":"Other","name":"RegulationDigital","retweets":0,"source":"<a href=\"http://ifttt.com\" rel=\"nofollow\">IFTTT</a>","text":"Hillary Clinton Joins The 'Make Silicon Valley Break Encryption' Bandwagon https://t.co/Z5y8sQYJNw","time_zone":"Other","words":["hillary","clinton","joins","the","'make","silicon","valley","break","encryption'","bandwagon","https://t.co/z5y8sqyjnw"],"filtered_words":["hillary","clinton","joins","'make","silicon","valley","break","encryption'","bandwagon","https://t.co/z5y8sqyjnw"],"features":{"type":1,"values":[0.011593355948571117,0.002829920593649149,0.014063050970435143,-0.042303118808195,-0.046180125791579485]},"prediction":16}
{"country":"Other","followers":80,"friends":251,"hashtags":[],"lang":"en","likes":0,"location":"West Virginia","name":"Bejour","retweets":0,"source":"<a href=\"http://twitter.com\" rel=\"nofollow\">Twitter Web Client</a>","text":"RT @realDonaldTrump: My family has the honor of being interviewed for a full hour by the legendary @BarbaraJWalters tonight @ABC - 10pmE. h…","time_zone":"Other","words":["rt","@realdonaldtrump:","my","family","has","the","honor","of","being","interviewed","for","a","full","hour","by","the","legendary","@barbarajwalters","tonight","@abc","-","10pme.","h…"],"filtered_words":["rt","@realdonaldtrump:","family","honor","interviewed","full","hour","legendary","@barbarajwalters","tonight","@abc","-","10pme.","h…"],"features":{"type":1,"values":[0.03647670143150857,0.06184835931552308,0.08124706378605749,0.0010563119846795286,-0.054156813837055645]},"prediction":10}
{"country":"Other","followers":90,"friends":58,"hashtags":["android","androidgames","gameinsight"],"lang":"ru","likes":0,"location":"St.-Petersburg","name":"Lanusino","retweets":0,"source":"","text":"Урожай собран - 1 500 еды! Ты тоже проверь свои грядки!  https://t.co/A0cWjZZrk3 #android, #androidgames, #gameinsight","time_zone":"St. Petersburg","words":["урожай","собран","-","1","500","еды!","ты","тоже","проверь","свои","грядки!","","https://t.co/a0cwjzzrk3","#android,","#androidgames,","#gameinsight"],"filtered_words":["урожай","собран","-","1","500","еды!","ты","тоже","проверь","свои","грядки!","","https://t.co/a0cwjzzrk3","#android,","#androidgames,","#gameinsight"],"features":{"type":1,"values":[-0.07220337324542925,-0.05576124892104417,-0.028547398251248524,0.046726605665753596,0.09536795259919018]},"prediction":17}
{"country":"Other","followers":95,"friends":0,"hashtags":[],"lang":"en","likes":0,"location":"New York, USA","name":"Veomtu Zaalmi","retweets":0,"source":"<a href=\"http://ifttt.com\" rel=\"nofollow\">IFTTT</a>","text":"iPhone 6 (4.7\") 64GB Unlocked (CDMA)(Verizon,Sprint,AT&amp;T, T-mobile, Cricket,etc) - Bid Now… https://t.co/fKwa8ufZct https://t.co/jgxKRHyIAr","time_zone":"Other","words":["iphone","6","(4.7\")","64gb","unlocked","(cdma)(verizon,sprint,at&amp;t,","t-mobile,","cricket,etc)","-","bid","now…","https://t.co/fkwa8ufzct","https://t.co/jgxkrhyiar"],"filtered_words":["iphone","6","(4.7\")","64gb","unlocked","(cdma)(verizon,sprint,at&amp;t,","t-mobile,","cricket,etc)","-","bid","now…","https://t.co/fkwa8ufzct","https://t.co/jgxkrhyiar"],"features":{"type":1,"values":[0.0025232255530471988,0.07231231854082301,0.06577174050303607,0.008414130084789717,-0.04356158594600856]},"prediction":2}
{"country":"Other","followers":101,"friends":40,"hashtags":[],"lang":"ja","likes":0,"location":"Other","name":"わわわら","retweets":0,"source":"<a href=\"http://japanjet.net\" rel=\"nofollow\">ジャパンニュースジェット</a>","text":"なにこれiPhoneだけでお金稼げた！笑\nみんなやればいいのに(^^)\nhttps://t.co/Ut4QuA6cXv\n\nかんたんw https://t.co/uVv32YWfQJ","time_zone":"Other","words":["なにこれiphoneだけでお金稼げた！笑","みんなやればいいのに(^^)","https://t.co/ut4qua6cxv","","かんたんw","https://t.co/uvv32ywfqj"],"filtered_words":["なにこれiphoneだけでお金稼げた！笑","みんなやればいいのに(^^)","https://t.co/ut4qua6cxv","","かんたんw","https://t.co/uvv32ywfqj"],"features":{"type":1,"values":[-0.036490263106922306,-0.00485440157353878,-0.006116127284864584,-0.03823945205658674,0.0060876648252209025]},"prediction":19}
{"country":"Other","followers":149,"friends":84,"hashtags":["coffeelove","luvtheme","iphoneshoot","leisureshoot","erwinjkrisnanda"],"lang":"in","likes":0,"location":"Surabaya, Indonesia","name":"Erwin J. Krisnanda","retweets":0,"source":"<a href=\"http://instagram.com\" rel=\"nofollow\">Instagram</a>","text":"Nemu lagi.. #coffeelove  #luvtheme  #iphoneshoot  #leisureshoot  #erwinjkrisnanda @ Hero Supermarket… https://t.co/pV4btruGjy","time_zone":"Other","words":["nemu","lagi..","#coffeelove","","#luvtheme","","#iphoneshoot","","#leisureshoot","","#erwinjkrisnanda","@","hero","supermarket…","https://t.co/pv4btrugjy"],"filtered_words":["nemu","lagi..","#coffeelove","","#luvtheme","","#iphoneshoot","","#leisureshoot","","#erwinjkrisnanda","@","hero","supermarket…","https://t.co/pv4btrugjy"],"features":{"type":1,"values":[-0.011724248031775157,-0.03134007006883621,0.002451541010911266,-0.06282801317671935,0.0023671886844870943]},"prediction":7}
{"country":"Other","followers":202,"friends":367,"hashtags":[],"lang":"en","likes":0,"location":"Florida, USA","name":"Jerry Jurski","retweets":0,"source":"<a href=\"http://twitter.com/download/android\" rel=\"nofollow\">Twitter for Android</a>","text":"RT @PatVPeters: Hillary LIES???? Gasp\n\nAP Fact Check Smashes Hillary Debate Claims https://t.co/uHgtTBMtJV","time_zone":"Other","words":["rt","@patvpeters:","hillary","lies????","gasp","","ap","fact","check","smashes","hillary","debate","claims","https://t.co/uhgttbmtjv"],"filtered_words":["rt","@patvpeters:","hillary","lies????","gasp","","ap","fact","check","smashes","hillary","debate","claims","https://t.co/uhgttbmtjv"],"features":{"type":1,"values":[0.009274560542378041,-0.016070429435265914,0.021301178195114647,-0.020851447712630033,-0.048498431752835]},"prediction":19}
{"country":"Other","followers":215,"friends":305,"hashtags":["WAFC"],"lang":"en","likes":0,"location":"Other","name":"Wigan Athletic News","retweets":0,"source":"<a href=\"http://draldevelopment.uk\" rel=\"nofollow\">Wigan Tahletic Twitter News</a>","text":"All the latest Wigan Athletic news on iPhone and iPad! https://t.co/hA4v7oFQZb #WAFC","time_zone":"Other","words":["all","the","latest","wigan","athletic","news","on","iphone","and","ipad!","https://t.co/ha4v7ofqzb","#wafc"],"filtered_words":["latest","wigan","athletic","news","iphone","ipad!","https://t.co/ha4v7ofqzb","#wafc"],"features":{"type":1,"values":[0.0076975347474217415,0.08299840008839965,0.030303005129098892,0.027884316514246166,-0.07849393715150654]},"prediction":13}
{"country":"Other","followers":236,"friends":85,"hashtags":[],"lang":"en","likes":0,"location":"Toronto, Ontario","name":"MarketingForJustice","retweets":0,"source":"<a href=\"http://ifttt.com\" rel=\"nofollow\">IFTTT</a>","text":"\"There are over 100 million iPhones now in use in the US https://t.co/idy4IBrVyC https://t.co/PGOvsArAXI\"https://t.co/3hD1QPwof6","time_zone":"Other","words":["\"there","are","over","100","million","iphones","now","in","use","in","the","us","https://t.co/idy4ibrvyc","https://t.co/pgovsaraxi\"https://t.co/3hd1qpwof6"],"filtered_words":["\"there","100","million","iphones","use","us","https://t.co/idy4ibrvyc","https://t.co/pgovsaraxi\"https://t.co/3hd1qpwof6"],"features":{"type":1,"values":[-0.0018201508792117238,1.462732325308025E-4,-0.0022704044822603464,0.016182156512513757,-0.0331532018026337]},"prediction":3}
{"country":"Other","followers":283,"friends":263,"hashtags":[],"lang":"en","likes":0,"location":"Other","name":"owen greene","retweets":0,"source":"<a href=\"http://twitter.com/download/iphone\" rel=\"nofollow\">Twitter for iPhone</a>","text":"RT @WORIDSTARHIPHOP: RT if you think this mozzarella stick would be a better president than Donald Trump. https://t.co/EGSCIKp0wX","time_zone":"Other","words":["rt","@woridstarhiphop:","rt","if","you","think","this","mozzarella","stick","would","be","a","better","president","than","donald","trump.","https://t.co/egscikp0wx"],"filtered_words":["rt","@woridstarhiphop:","rt","think","mozzarella","stick","better","president","donald","trump.","https://t.co/egscikp0wx"],"features":{"type":1,"values":[0.006660163741220128,-0.03141952306032181,0.012925580313259905,0.012083276979286562,0.030635892328890888]},"prediction":6}
{"country":"Other","followers":320,"friends":31,"hashtags":["Trump2016","IAForums"],"lang":"en","likes":0,"location":"Cut Off, LA","name":"John LeBoeuf Sr.","retweets":0,"source":"<a href=\"http://twitter.com/download/iphone\" rel=\"nofollow\">Twitter for iPhone</a>","text":"RT @realDonaldTrump: A great evening in Iowa! Thank you Des Moines Area Community College for a great forum! #Trump2016 #IAForums https://t…","time_zone":"Other","words":["rt","@realdonaldtrump:","a","great","evening","in","iowa!","thank","you","des","moines","area","community","college","for","a","great","forum!","#trump2016","#iaforums","https://t…"],"filtered_words":["rt","@realdonaldtrump:","great","evening","iowa!","thank","des","moines","area","community","college","great","forum!","#trump2016","#iaforums","https://t…"],"features":{"type":1,"values":[-0.013310976879438385,0.030706538469530642,0.018008937942795455,-0.03063860602560453,0.0013358520809561014]},"prediction":8}
{"country":"Other","followers":357,"friends":972,"hashtags":[],"lang":"en","likes":0,"location":"Bogor Selatan, West Java","name":"Nur Sawal Udin","retweets":0,"source":"<a href=\"http://twittbot.net/\" rel=\"nofollow\">twittbot.net</a>","text":"Money Lover APK 3.0.7 - Free Finance App for Android How to manage your money ef  https://t.co/KH8qep5qHX","time_zone":"Jakarta","words":["money","lover","apk","3.0.7","-","free","finance","app","for","android","how","to","manage","your","money","ef","","https://t.co/kh8qep5qhx"],"filtered_words":["money","lover","apk","3.0.7","-","free","finance","app","android","manage","money","ef","","https://t.co/kh8qep5qhx"],"features":{"type":1,"values":[0.007734745408275298,-0.02031030100105064,0.02670887977417026,-0.04074580717549127,-0.020795058592089584]},"prediction":15}
{"country":"Other","followers":479,"friends":888,"hashtags":["iphone","iphonegames","gameinsight"],"lang":"tr","likes":0,"location":"Other","name":"yasemin çelik","retweets":0,"source":"<a href=\"http://bit.ly/tribez_itw\" rel=\"nofollow\">The Tribez</a>","text":"10,015 altın sikke topladım! https://t.co/cE2n4ci0jB #iphone, #iphonegames, #gameinsight","time_zone":"Other","words":["10,015","altın","sikke","topladım!","https://t.co/ce2n4ci0jb","#iphone,","#iphonegames,","#gameinsight"],"filtered_words":["10,015","altın","sikke","topladım!","https://t.co/ce2n4ci0jb","#iphone,","#iphonegames,","#gameinsight"],"features":{"type":1,"values":[-0.016950503108091652,-0.01849966566078365,-0.002421525976387784,0.006150619825348258,0.031114727491512895]},"prediction":6}
{"country":"Other","followers":553,"friends":241,"hashtags":[],"lang":"ja","likes":0,"location":"基本DM返しませ~ん","name":"じゅじゅ@メンヘラ","retweets":0,"source":"<a href=\"http://twitcasting.tv/\" rel=\"nofollow\">TwitCasting</a>","text":"夜更かしさんおいで~/モイ！iPhoneからキャス配信中 / コメントよろしゅう https://t.co/5ZnaGwGbF8","time_zone":"JST","words":["夜更かしさんおいで~/モイ！iphoneからキャス配信中","/","コメントよろしゅう","https://t.co/5znagwgbf8"],"filtered_words":["夜更かしさんおいで~/モイ！iphoneからキャス配信中","/","コメントよろしゅう","https://t.co/5znagwgbf8"],"features":{"type":1,"values":[0.002104151761159301,0.019054431235417724,0.056148392613977194,0.006654850207269192,-0.02841914538294077]},"prediction":2}
{"country":"Other","followers":570,"friends":673,"hashtags":["Obama"],"lang":"en","likes":0,"location":"Kansas City, MO","name":"Lore Meltzer","retweets":0,"source":"<a href=\"http://twitter.com/#!/download/ipad\" rel=\"nofollow\">Twitter for iPad</a>","text":"@SlimTim925 @Trump_time @realDonaldTrump ~Vaguely remember #Obama taking same oath? Now he's aiding enemy &amp; placing citizens in harm's way.","time_zone":"Central Time (US & Canada)","words":["@slimtim925","@trump_time","@realdonaldtrump","~vaguely","remember","#obama","taking","same","oath?","now","he's","aiding","enemy","&amp;","placing","citizens","in","harm's","way."],"filtered_words":["@slimtim925","@trump_time","@realdonaldtrump","~vaguely","remember","#obama","taking","oath?","aiding","enemy","&amp;","placing","citizens","harm's","way."],"features":{"type":1,"values":[0.01211144804644088,0.01058972580358386,0.0029390051340063414,-0.007422237719098727,-0.0079831146945556]},"prediction":5}
{"country":"Other","followers":733,"friends":562,"hashtags":[],"lang":"en","likes":0,"location":"Other","name":"TRUMP FOR 2016!!","retweets":0,"source":"<a href=\"https://mobile.twitter.com\" rel=\"nofollow\">Mobile Web (M5)</a>","text":"RT @GOP_Left_ME: @CplSoletrain @jjenningsUSA @pattimagnon BS, After the other 14 repubs get out thing will change. Also Trump will slay her…","time_zone":"Other","words":["rt","@gop_left_me:","@cplsoletrain","@jjenningsusa","@pattimagnon","bs,","after","the","other","14","repubs","get","out","thing","will","change.","also","trump","will","slay","her…"],"filtered_words":["rt","@gop_left_me:","@cplsoletrain","@jjenningsusa","@pattimagnon","bs,","14","repubs","get","thing","change.","also","trump","slay","her…"],"features":{"type":1,"values":[0.0314217464843144,0.01950233696649472,0.01972389469544093,-0.0015946030461539825,-0.007823953901727994]},"prediction":5}
{"country":"Other","followers":740,"friends":575,"hashtags":[],"lang":"in","likes":0,"location":"Malaysiaaaa","name":".","retweets":0,"source":"<a href=\"http://twitter.com/download/iphone\" rel=\"nofollow\">Twitter for iPhone</a>","text":"@SyafiqahNidzam kat mana tu? Eh okay apa hahah btw akak penjual iphone and casing hahah kalau nak beli pm lah ye hahah","time_zone":"Kuala Lumpur","words":["@syafiqahnidzam","kat","mana","tu?","eh","okay","apa","hahah","btw","akak","penjual","iphone","and","casing","hahah","kalau","nak","beli","pm","lah","ye","hahah"],"filtered_words":["@syafiqahnidzam","kat","mana","tu?","eh","okay","apa","hahah","btw","akak","penjual","iphone","casing","hahah","kalau","nak","beli","pm","lah","ye","hahah"],"features":{"type":1,"values":[0.002606585954449006,0.05352953040883655,0.0635860383599287,0.03001816113967271,-0.07491004635535535]},"prediction":2}
{"country":"Other","followers":839,"friends":587,"hashtags":[],"lang":"ja","likes":0,"location":"有楽町とか舞浜とか太正時代とか","name":"裕*サクラ大戦19周年!!","retweets":0,"source":"<a href=\"http://twitcasting.tv/\" rel=\"nofollow\">TwitCasting</a>","text":"モイ！Androidからキャス配信中 - https://t.co/rCnrhtyLSs","time_zone":"Hawaii","words":["モイ！androidからキャス配信中","-","https://t.co/rcnrhtylss"],"filtered_words":["モイ！androidからキャス配信中","-","https://t.co/rcnrhtylss"],"features":{"type":1,"values":[0.058586377650499344,0.0885933805257082,0.11332481354475021,-0.010736841708421707,-0.07961331331171095]},"prediction":10}
{"country":"Other","followers":953,"friends":13,"hashtags":["Music","iTunes","iPhone","Apple"],"lang":"en","likes":0,"location":"Other","name":"iTunes Top 10 Songs","retweets":0,"source":"<a href=\"http://blog.77jp.net\" rel=\"nofollow\">iTunes Store Top 10 Songs</a>","text":"United States 69. Shut Up and Dance - WALK THE MOON https://t.co/WXUnwzFmZN #Music #iTunes #iPhone #Apple","time_zone":"Other","words":["united","states","69.","shut","up","and","dance","-","walk","the","moon","https://t.co/wxunwzfmzn","#music","#itunes","#iphone","#apple"],"filtered_words":["united","states","69.","shut","dance","-","walk","moon","https://t.co/wxunwzfmzn","#music","#itunes","#iphone","#apple"],"features":{"type":1,"values":[0.0339327953182734,0.0014302717665067087,0.00830832335094993,-0.027857600908296615,-0.007807666435837746]},"prediction":15}
{"country":"Other","followers":1308,"friends":706,"hashtags":[],"lang":"en","likes":0,"location":"Everywhere","name":"Ann Foster","retweets":0,"source":"<a href=\"http://twitter.com/download/iphone\" rel=\"nofollow\">Twitter for iPhone</a>","text":"RT @thejeffoneal: i hope the question someday is not would you go back and kill baby trump","time_zone":"Saskatchewan","words":["rt","@thejeffoneal:","i","hope","the","question","someday","is","not","would","you","go","back","and","kill","baby","trump"],"filtered_words":["rt","@thejeffoneal:","hope","question","someday","go","back","kill","baby","trump"],"features":{"type":1,"values":[0.04513938296586276,0.010768171260133387,0.02431595623493195,-0.07151104453951121,-0.02465676898136735]},"prediction":16}
{"country":"Other","followers":1720,"friends":1374,"hashtags":[],"lang":"en","likes":0,"location":"1001, Glassmanor","name":"ISMOKEDOPE","retweets":0,"source":"<a href=\"http://twitter.com/download/android\" rel=\"nofollow\">Twitter for Android</a>","text":"RT @admire_mir: The most annoying thing when you get the 16gb iPhone 😂😱 https://t.co/948K51gbUd","time_zone":"Quito","words":["rt","@admire_mir:","the","most","annoying","thing","when","you","get","the","16gb","iphone","😂😱","https://t.co/948k51gbud"],"filtered_words":["rt","@admire_mir:","annoying","thing","get","16gb","iphone","😂😱","https://t.co/948k51gbud"],"features":{"type":1,"values":[-0.0033972224013672932,0.018085273086196844,0.00994638746811284,-0.025548706245091226,-0.024023185949772596]},"prediction":8}
{"country":"Other","followers":1732,"friends":2447,"hashtags":[],"lang":"en","likes":0,"location":"San Francisco","name":"Bujho - 4 Pic 1 Word","retweets":0,"source":"<a href=\"http://tweetfull.com\" rel=\"nofollow\">Tweet Full</a>","text":"RT @BuzzWiki: \"Twist\" cannot be stopped. The iPhone game, which is a twist on the classic arcade game \"Tempest,\"  was released… https://t.c…","time_zone":"Other","words":["rt","@buzzwiki:","\"twist\"","cannot","be","stopped.","the","iphone","game,","which","is","a","twist on","the","classic","arcade","game \"tempest,\""," was","released…","https://t.c…"],"filtered_words":["rt","@buzzwiki:","\"twist\"","stopped.","iphone","game,","twist on","classic","arcade","game \"tempest,\""," was","released…","https://t.c…"],"features":{"type":1,"values":[0.017901718616485596,0.0029972723344914042,0.019026407721237495,-0.008626077610712785,-0.04385318320531112]},"prediction":16}
{"country":"Other","followers":2482,"friends":2506,"hashtags":["Trump2016","TrumpTrain"],"lang":"en","likes":0,"location":"North Carolina, USA","name":"David Pollock","retweets":0,"source":"<a href=\"http://twitter.com\" rel=\"nofollow\">Twitter Web Client</a>","text":"We finally have a voice with @realDonaldTrump, Let’s do our part &amp; VOTE IN THE R PRIMARY 4 #Trump2016 #TrumpTrain  https://t.co/uf2XEGPVxt","time_zone":"Eastern Time (US & Canada)","words":["we","finally","have","a","voice","with","@realdonaldtrump,","let’s","do","our","part","&amp;","vote","in","the","r","primary","4","#trump2016","#trumptrain","","https://t.co/uf2xegpvxt"],"filtered_words":["finally","voice","@realdonaldtrump,","let’s","part","&amp;","vote","r","primary","4","#trump2016","#trumptrain","","https://t.co/uf2xegpvxt"],"features":{"type":1,"values":[0.016114809018160616,-0.0033368605322071482,0.01250550683055605,-0.04238136693103505,-0.016336773854813403]},"prediction":15}
{"country":"Other","followers":3905,"friends":3841,"hashtags":["Mizzou","LibCrib","Hillary2016","UniteBlue"],"lang":"en","likes":0,"location":"United States","name":"CruzMissile!!","retweets":0,"source":"<a href=\"http://ifttt.com\" rel=\"nofollow\">IFTTT</a>","text":"DeadNed88 Sen. Cruz: My Flat Tax Plan Would Abolish the IRS | #Mizzou #LibCrib #Hillary2016 #UniteBlue https://t.co/2yP1orXHXB","time_zone":"Eastern Time (US & Canada)","words":["deadned88","sen.","cruz:","my","flat","tax","plan","would","abolish","the","irs","|","#mizzou","#libcrib","#hillary2016","#uniteblue","https://t.co/2yp1orxhxb"],"filtered_words":["deadned88","sen.","cruz:","flat","tax","plan","abolish","irs","|","#mizzou","#libcrib","#hillary2016","#uniteblue","https://t.co/2yp1orxhxb"],"features":{"type":1,"values":[-0.014587421302816697,0.02316359064674803,0.021008938617472137,-0.008522245766861098,-0.020037565313811814]},"prediction":5}
{"country":"Other","followers":179443,"friends":165503,"hashtags":["DonaldTrump","TCOT","Trump2016"],"lang":"en","likes":0,"location":"REPUBLIC OF TEXAS","name":"DR. TWEET, Ph.D.","retweets":0,"source":"<a href=\"http://twitter.com/#!/download/ipad\" rel=\"nofollow\">Twitter for iPad</a>","text":"RT @ChristieC733: Secret Service Investigates #DonaldTrump Worcester Death Threat\n\n#TCOT \n#Trump2016\n \n✅ https://t.co/9wm4XQBUBl https://t.…","time_zone":"Other","words":["rt","@christiec733:","secret","service","investigates","#donaldtrump","worcester","death","threat","","#tcot","","#trump2016","","","✅","https://t.co/9wm4xqbubl","https://t.…"],"filtered_words":["rt","@christiec733:","secret","service","investigates","#donaldtrump","worcester","death","threat","","#tcot","","#trump2016","","","✅","https://t.co/9wm4xqbubl","https://t.…"],"features":{"type":1,"values":[-0.028148133747486603,-0.06088800448924303,0.024651004881080654,-0.042090020039015345,-0.015129640957133636]},"prediction":0}
